mcp_server_wlzdgk/2_wlzd.js
mcp_server_wlzdgk/__init__.py
mcp_server_wlzdgk/__main__.py
mcp_server_wlzdgk/server.py
mcp_server_wlzdgk/switch_name.txt
mcp_server_wlzdgk/tmntype.txt
mcp_server_wlzdgk-1.3.0.dist-info/METADATA
mcp_server_wlzdgk-1.3.0.dist-info/WHEEL
mcp_server_wlzdgk-1.3.0.dist-info/entry_points.txt
mcp_server_wlzdgk-1.3.0.dist-info/RECORD
