Metadata-Version: 2.4
Name: mcp-server-wlzdgk
Version: 1.3.0
Summary: Add your description here
Author-email: guhuayue <guhuayue185@gmail.com>
Keywords: ip,llm,mac,mcp
Classifier: Development Status :: 4 - Beta
Classifier: Intended Audience :: Developers
Classifier: License :: OSI Approved :: MIT License
Classifier: Programming Language :: Python :: 3
Classifier: Programming Language :: Python :: 3.10
Requires-Python: >=3.10
Requires-Dist: mcp>=1.10.1
Requires-Dist: pycryptodome>=3.23.0
Requires-Dist: pyexecjs>=1.5.1
Requires-Dist: requests>=2.32.4
